cvframes/__init__.py
cvframes/cli.py
cvframes/iterate.py
cvframes/web/__init__.py
cvframes/web/client.py
cvframes/web/server.py
cvframes/web/static/index.html
cv_frames-0.0.3.dist-info/METADATA
cv_frames-0.0.3.dist-info/WHEEL
cv_frames-0.0.3.dist-info/entry_points.txt
cv_frames-0.0.3.dist-info/top_level.txt
cv_frames-0.0.3.dist-info/RECORD
