Metadata-Version: 2.4
Name: cv-frames
Version: 0.0.3
Summary: Read frames from OpenCV like humans
Requires-Dist: opencv-python
Requires-Dist: numpy
Requires-Dist: click
Provides-Extra: web
Requires-Dist: aiohttp; extra == "web"
